{"batchcode": "000227A", "histogram": {"Angioedema": 1, "Arrhythmia": 1, "Blindness unilateral": 1, "COVID-19 immunisation": 1, "Cardiac failure": 1, "Ear congestion": 1, "Head discomfort": 1, "Headache": 1, "Influenza like illness": 1, "Neurosensory hypoacusis": 1, "Pruritus": 1, "Rash": 1, "Urticaria": 1, "Vaccination site movement impairment": 1, "Vaccination site pain": 1, "Vitreous haemorrhage": 1, "Vomiting": 1, "Wheezing": 1}, "Life Threatening Illnesses": 0, "Company": "MODERNA", "Adverse Reaction Reports": 6, "Disabilities": 1, "Deaths": 0}