{"batchcode": "0004M20A", "histograms": [{"histogram": {"Anaemia": 1, "Liver function test increased": 1}, "batchcodes": ["0004M20A", "031M20A"]}, {"histogram": {"Product administered to patient of inappropriate age": 1, "Vaccination site erythema": 1, "Vaccination site pruritus": 1, "Vaccination site warmth": 1}, "batchcodes": ["0004M20A"]}], "Deaths": 0, "Lethality": null, "Company": "MODERNA", "Adverse Reaction Reports": 3, "Disabilities": 0, "Life Threatening Illnesses": 0, "Severe reports": null}