{"Adverse Reaction Reports": 47, "Company": "MODERNA", "Deaths": 0, "Disabilities": 2, "Hospitalizations": 7, "Life-Threatening Illnesses": 1, "batchcode": "002821A", "histogram": {"Abdominal pain": 3, "Abdominal pain upper": 2, "Acoustic stimulation tests abnormal": 1, "Aggression": 1, "Aphasia": 1, "Arthralgia": 6, "Asthenia": 3, "Balance disorder": 1, "Bedridden": 1, "Blood test": 4, "Blood test normal": 1, "Body temperature increased": 1, "Bone pain": 2, "COVID-19": 2, "Cardiac flutter": 1, "Chest X-ray": 1, "Chest pain": 2, "Chills": 10, "Choking": 1, "Computerised tomogram": 1, "Computerised tomogram abdomen normal": 1, "Computerised tomogram head normal": 1, "Computerised tomogram thorax": 1, "Condition aggravated": 1, "Contusion": 1, "Cough": 2, "Deafness neurosensory": 1, "Deafness unilateral": 1, "Dermatologic examination": 1, "Diarrhoea": 5, "Differential white blood cell count": 1, "Dizziness": 5, "Dysarthria": 1, "Dyskinesia": 1, "Dysphagia": 1, "Dyspnoea": 4, "Electrocardiogram": 1, "Encephalitis autoimmune": 1, "Erythema": 2, "Eye swelling": 1, "Fall": 1, "Fatigue": 11, "Feeling abnormal": 3, "Feeling hot": 2, "Flushing": 1, "Full blood count": 1, "Gait disturbance": 1, "Gait inability": 1, "Gastrooesophageal reflux disease": 1, "Gastrostomy": 1, "General physical health deterioration": 1, "Gingival bleeding": 1, "Headache": 11, "Heart rate": 2, "Heart rate increased": 3, "Herpes zoster": 1, "Hyperhidrosis": 2, "Hypoaesthesia": 2, "Illness": 2, "Immunoglobulin therapy": 1, "Impaired quality of life": 1, "Incontinence": 1, "Incorrect dose administered": 1, "Infection": 1, "Injection site erythema": 1, "Injection site pain": 3, "Injection site pruritus": 2, "Injection site rash": 1, "Injection site swelling": 1, "Insomnia": 1, "Irritability": 1, "Joint swelling": 1, "Laboratory test normal": 1, "Labour pain": 1, "Lethargy": 2, "Limb discomfort": 2, "Loss of personal independence in daily activities": 1, "Lumbar puncture normal": 1, "Lymphadenopathy": 1, "Magnetic resonance imaging": 1, "Magnetic resonance imaging head normal": 2, "Magnetic resonance imaging spinal normal": 1, "Mobility decreased": 1, "Mouth haemorrhage": 1, "Muscular weakness": 3, "Musculoskeletal chest pain": 1, "Myalgia": 7, "Nausea": 7, "Neck pain": 3, "Onychomadesis": 1, "Oropharyngeal discomfort": 1, "Oropharyngeal pain": 1, "Osteopenia": 1, "Pain": 6, "Pain in extremity": 15, "Pallor": 1, "Palpitations": 1, "Paraesthesia": 1, "Paralysis": 1, "Peripheral swelling": 3, "Personality change": 1, "Plasmapheresis": 1, "Pruritus": 1, "Pulmonary congestion": 1, "Pyrexia": 6, "Rash": 2, "Rash erythematous": 1, "Rash papular": 1, "Rash pruritic": 1, "Rhinorrhoea": 1, "SARS-CoV-2 test": 1, "SARS-CoV-2 test negative": 1, "SARS-CoV-2 test positive": 1, "Scan normal": 1, "Scan with contrast normal": 1, "Severe acute respiratory syndrome": 2, "Sitting disability": 1, "Skin warm": 1, "Somnolence": 1, "Sudden hearing loss": 1, "Syncope": 1, "Tenderness": 1, "Tinnitus": 1, "Tremor": 1, "Urine analysis": 2, "Urticaria": 1, "Vaccination site pain": 2, "Vaccine breakthrough infection": 1, "Vision blurred": 3, "Vomiting": 7, "X-ray": 2}}