{"batchcode": "003AA21", "histograms": [{"histogram": {"Cough": 1, "Dyspepsia": 1, "Eructation": 1, "Gastrointestinal sounds abnormal": 1, "Influenza virus test negative": 1, "Oropharyngeal pain": 1, "Respiratory tract congestion": 1, "SARS-CoV-2 test negative": 1, "Sexual dysfunction": 1, "Streptococcus test negative": 1, "Throat tightness": 1}, "batchcodes": ["003AA21"]}], "Adverse Reaction Reports": 1, "Deaths": 0, "Disabilities": 0, "Life Threatening Illnesses": 0, "Company": "MODERNA", "Severe reports": null, "Lethality": null}