{"Adverse Reaction Reports": 5, "Company": "MODERNA", "Deaths": 0, "Disabilities": 0, "Hospitalizations": 0, "Life-Threatening Illnesses": 0, "batchcode": "00821A", "histogram": {"Balance disorder": 1, "Chills": 2, "Decreased appetite": 1, "Dizziness": 1, "Electrocardiogram": 1, "Fatigue": 2, "Heart rate increased": 1, "Injection site erythema": 1, "Injection site induration": 1, "Lymphadenopathy": 1, "Lymphoedema": 1, "Migraine": 1, "Myalgia": 1, "Nausea": 1, "Pain": 2, "Pain in extremity": 1, "Pain of skin": 1, "Paraesthesia": 1, "Paraesthesia oral": 1, "Peripheral swelling": 2, "Pruritus": 2, "Pyrexia": 1, "Rash erythematous": 1, "Skin warm": 1, "Tremor": 1}}