{"batchcode": "011L2OA", "histogram": {"Headache": 5, "Pain": 5, "Injection site erythema": 4, "Chills": 3, "Injection site pain": 3, "Body temperature increased": 2, "Erythema": 2, "Fatigue": 2, "Hyperhidrosis": 2, "Injection site pruritus": 2, "Injection site urticaria": 2, "Nausea": 2, "Pyrexia": 2, "Rash": 2, "Axillary pain": 1, "Cardiac arrest": 1, "Chest discomfort": 1, "Death": 1, "Dysgeusia": 1, "Dysphagia": 1, "Eye paraesthesia": 1, "Feeling hot": 1, "Hyperventilation": 1, "Hypoaesthesia oral": 1, "Initial insomnia": 1, "Injection site rash": 1, "Injection site reaction": 1, "Injection site swelling": 1, "Injection site warmth": 1, "Insomnia": 1, "Lethargy": 1, "Lymphadenopathy": 1, "Malaise": 1, "Paraesthesia oral": 1, "Pruritus": 1, "Rash erythematous": 1, "Rash pruritic": 1, "Sensation of foreign body": 1, "Sensory loss": 1, "Skin warm": 1, "Swelling": 1, "Swollen tongue": 1, "Unevaluable event": 1, "Vaccination site erythema": 1, "Vaccination site pain": 1, "Vaccination site reaction": 1, "Vaccination site swelling": 1, "Wheezing": 1}, "Hospitalizations": 2, "Adverse Reaction Reports": 18, "Disabilities": 0, "Deaths": 1, "Life-Threatening Illnesses": 0, "Company": "MODERNA"}