{"batchcode": "0222M20A", "histograms": [{"histogram": {"COVID-19": 1, "Chronic obstructive pulmonary disease": 1, "Cough": 1, "Death": 1, "Dyspnoea": 1, "Fall": 1, "Oxygen saturation decreased": 1, "Pneumonia": 1, "SARS-CoV-2 test positive": 1}, "batchcodes": ["0222M20A", "069F21A"]}, {"histogram": {"Asthenia": 1, "COVID-19": 1, "Chest pain": 1, "Confusional state": 1, "Cough": 1, "Depressed level of consciousness": 1, "Eye pain": 1, "Fatigue": 1, "Headache": 1, "Loss of consciousness": 1, "Nausea": 1, "SARS-CoV-2 test positive": 1, "Vomiting": 1}, "batchcodes": ["0222M20A"]}], "Life Threatening Illnesses": 0, "Adverse Reaction Reports": 4, "Deaths": 1, "Company": "MODERNA", "Severe reports": null, "Lethality": null, "Disabilities": 0}