{"batchcode": "028L28A", "histograms": [{"histogram": {"Blood test": 1, "Cardiac stress test": 1, "Catheterisation cardiac": 1, "Computerised tomogram coronary artery": 1, "Coronary arterial stent insertion": 1, "Dyspnoea exertional": 1, "Echocardiogram": 1, "Electrocardiogram": 1, "Fatigue": 1, "Headache": 1, "Hypertension": 1, "Inflammation": 1, "Pain": 1}, "batchcodes": ["028L28A", "039K20-2A"]}, {"histogram": {"Death": 1, "Dementia": 1}, "batchcodes": ["028L28A"]}], "Adverse Reaction Reports": 2, "Deaths": 1, "Disabilities": 0, "Life Threatening Illnesses": 1, "Company": "MODERNA", "Severe reports": null, "Lethality": null}