{"batchcode": "031120A", "histogram": {"Fatigue": 9, "Pain in extremity": 8, "Pyrexia": 7, "Headache": 6, "Nausea": 5, "Pain": 5, "Chills": 4, "Dizziness": 4, "Myalgia": 4, "Vomiting": 4, "Arthralgia": 3, "Chest discomfort": 3, "Decreased appetite": 3, "Erythema": 3, "Injection site erythema": 3, "Injection site pain": 3, "Injection site swelling": 3, "Pruritus": 3, "Vaccination site pain": 3, "Asthenia": 2, "Body temperature": 2, "Diarrhoea": 2, "Eye pruritus": 2, "Flushing": 2, "Influenza like illness": 2, "Palpitations": 2, "Rash": 2, "Swelling face": 2, "Taste disorder": 2, "Tremor": 2, "Urticaria": 2, "Vaccination site erythema": 2, "Anaphylactic reaction": 1, "Angina pectoris": 1, "Asthma": 1, "Atrial fibrillation": 1, "Blood test": 1, "Body temperature increased": 1, "Burning sensation": 1, "Cardiac flutter": 1, "Cardiac monitoring": 1, "Cardiac stress test": 1, "Cognitive disorder": 1, "Computerised tomogram thorax": 1, "Cough": 1, "Diplegia": 1, "Disturbance in attention": 1, "Dysgeusia": 1, "Dyspnoea": 1, "Eye swelling": 1, "Feeling hot": 1, "Groin pain": 1, "Hypertension": 1, "Illness": 1, "Immediate post-injection reaction": 1, "Inappropriate schedule of product administration": 1, "Injection site pruritus": 1, "Lacrimation increased": 1, "Lymphadenopathy": 1, "Malaise": 1, "Mass excision": 1, "Mobility decreased": 1, "Mouth swelling": 1, "Muscle spasms": 1, "Musculoskeletal pain": 1, "Pallor": 1, "Parosmia": 1, "Pulmonary artery thrombosis": 1, "Rash erythematous": 1, "Rash papular": 1, "Rash pruritic": 1, "Salivary hypersecretion": 1, "Skin swelling": 1, "Sleep disorder": 1, "Tenderness": 1, "Thrombophlebitis superficial": 1, "Tooth infection": 1, "Vaccination site pruritus": 1, "Vaccination site warmth": 1, "Vertigo": 1}, "Disabilities": 0, "Adverse Reaction Reports": 41, "Deaths": 0, "Life Threatening Illnesses": 0, "Company": "MODERNA"}