{"Adverse Reaction Reports": 213, "Company": "MODERNA", "Deaths": 39, "Disabilities": 2, "Hospitalizations": 23, "Life-Threatening Illnesses": 1, "batchcode": "032H20A", "histogram": {"Abdominal discomfort": 2, "Abdominal mass": 1, "Abdominal pain": 4, "Abdominal pain upper": 1, "Acne": 1, "Acute respiratory failure": 4, "Anal incontinence": 1, "Anosmia": 1, "Anticoagulant therapy": 1, "Anxiety": 5, "Arrhythmia": 1, "Arthralgia": 10, "Asphyxia": 1, "Aspiration": 1, "Asthenia": 9, "Atelectasis": 1, "Atypical pneumonia": 1, "Axillary pain": 2, "Back pain": 1, "Blood chloride decreased": 1, "Blood chloride normal": 1, "Blood creatine phosphokinase increased": 1, "Blood creatinine normal": 1, "Blood culture positive": 1, "Blood potassium decreased": 1, "Blood pressure abnormal": 1, "Blood pressure fluctuation": 1, "Blood pressure increased": 1, "Blood sodium abnormal": 1, "Blood sodium normal": 1, "Blood test": 1, "Blood test abnormal": 1, "Blood urea increased": 1, "Body temperature": 1, "Body temperature increased": 9, "Breakthrough COVID-19": 4, "COVID-19": 24, "COVID-19 pneumonia": 4, "Carbon dioxide increased": 1, "Cardiac arrest": 2, "Cardiac failure": 2, "Cardiac stress test": 1, "Cardiopulmonary failure": 1, "Cellulitis": 2, "Chest X-ray": 2, "Chest X-ray abnormal": 5, "Chest discomfort": 1, "Chest pain": 3, "Chills": 13, "Clostridium test": 1, "Cold sweat": 1, "Colonoscopy": 1, "Computerised tomogram": 2, "Computerised tomogram abnormal": 1, "Computerised tomogram normal": 1, "Computerised tomogram thorax": 1, "Condition aggravated": 4, "Confusional state": 1, "Cough": 4, "Cyanosis": 1, "Death": 26, "Decreased appetite": 8, "Dementia Alzheimer's type": 2, "Dermatitis": 1, "Diabetes mellitus": 2, "Dialysis": 1, "Diarrhoea": 5, "Diet refusal": 1, "Discomfort": 1, "Dizziness": 13, "Dry mouth": 1, "Dysarthria": 1, "Dysgeusia": 2, "Dysphagia": 2, "Dyspnoea": 14, "Dyspnoea exertional": 1, "Electrocardiogram": 2, "Endoscopy": 1, "Erythema": 10, "Expired product administered": 3, "Exposure to SARS-CoV-2": 1, "Extra dose administered": 4, "Eye pruritus": 1, "Eye swelling": 1, "Facial paralysis": 1, "Factor V Leiden mutation": 1, "Fatigue": 20, "Feeding disorder": 1, "Feeling abnormal": 4, "Feeling hot": 3, "Fibrin D dimer increased": 1, "Flushing": 2, "Foreign body in throat": 1, "Gastrointestinal pain": 1, "General physical health deterioration": 2, "Haematocrit decreased": 1, "Haemoglobin": 1, "Haemoglobin decreased": 1, "Headache": 20, "Heart rate decreased": 1, "Heart rate increased": 6, "Heart rate irregular": 1, "Hemiparesis": 1, "Herpes zoster": 2, "Hyperhidrosis": 6, "Hypersensitivity": 1, "Hypoaesthesia": 5, "Hypoaesthesia oral": 2, "Hypokalaemia": 1, "Hypokinesia": 1, "Hypophagia": 2, "Hypotension": 4, "Hypotonia": 1, "Hypoxia": 3, "Illness": 1, "Immediate post-injection reaction": 2, "Impaired work ability": 4, "Inappropriate schedule of product administration": 1, "Infection": 1, "Influenza virus test negative": 1, "Injected limb mobility decreased": 1, "Injection site cellulitis": 2, "Injection site erythema": 19, "Injection site extravasation": 1, "Injection site induration": 1, "Injection site inflammation": 1, "Injection site irritation": 3, "Injection site mass": 1, "Injection site pain": 14, "Injection site pruritus": 12, "Injection site rash": 6, "Injection site reaction": 3, "Injection site scab": 1, "Injection site swelling": 13, "Injection site urticaria": 2, "Injection site warmth": 9, "Insomnia": 1, "Interchange of vaccine products": 1, "Interstitial lung disease": 1, "Joint stiffness": 1, "Laboratory test": 2, "Lactic acidosis": 1, "Lethargy": 6, "Leukocytosis": 1, "Lip pruritus": 1, "Lip swelling": 2, "Lung opacity": 2, "Lymphadenitis": 1, "Lymphadenopathy": 9, "Magnetic resonance imaging": 1, "Malaise": 5, "Metabolic function test": 1, "Migraine": 2, "Mobility decreased": 4, "Mouth swelling": 1, "Muscle spasms": 3, "Muscle tightness": 1, "Muscle twitching": 2, "Musculoskeletal chest pain": 1, "Musculoskeletal stiffness": 3, "Myalgia": 5, "Myocardial infarction": 1, "Nasal herpes": 1, "Nasal oedema": 1, "Nasopharyngitis": 1, "Nausea": 15, "Neck pain": 1, "Needle issue": 2, "Neurological symptom": 1, "Night sweats": 1, "No adverse event": 4, "Ocular discomfort": 1, "Ocular hyperaemia": 1, "Oesophagogastroduodenoscopy": 2, "Oral pain": 1, "Oral pruritus": 1, "Oropharyngeal discomfort": 1, "Oropharyngeal pain": 1, "Oxygen saturation decreased": 5, "Pain": 23, "Pain in extremity": 15, "Pain in jaw": 1, "Pallor": 1, "Palpitations": 1, "Papule": 1, "Paraesthesia": 1, "Paraesthesia oral": 2, "Paranasal sinus discomfort": 3, "Parosmia": 1, "Peripheral swelling": 5, "Pharyngeal swelling": 1, "Platelet count decreased": 1, "Pleural effusion": 1, "Pneumonia": 1, "Pneumonia aspiration": 1, "Pneumonia bacterial": 1, "Portal vein thrombosis": 1, "Product administered to patient of inappropriate age": 8, "Product storage error": 2, "Productive cough": 1, "Pruritus": 13, "Pulmonary embolism": 1, "Pulmonary pain": 1, "Pyrexia": 16, "Rash": 8, "Rash erythematous": 3, "Rash macular": 2, "Rash papular": 3, "Rash pruritic": 4, "Rash vesicular": 1, "Rectal haemorrhage": 1, "Red blood cell count increased": 1, "Respiratory arrest": 1, "Respiratory disorder": 1, "Respiratory distress": 2, "Respiratory failure": 1, "Respiratory tract congestion": 1, "Respiratory tract irritation": 1, "SARS-CoV-2 test": 2, "SARS-CoV-2 test negative": 5, "SARS-CoV-2 test positive": 22, "Sepsis": 1, "Sinus congestion": 1, "Sinus headache": 1, "Sinus operation": 1, "Skin burning sensation": 1, "Skin odour abnormal": 1, "Skin reaction": 2, "Skin warm": 8, "Sleep disorder": 1, "Somnolence": 2, "Stomatitis": 1, "Stridor": 1, "Swelling": 8, "Swelling face": 1, "Swollen tongue": 3, "Tachycardia": 1, "Tachypnoea": 1, "Throat irritation": 2, "Throat tightness": 1, "Tongue disorder": 1, "Transfusion": 1, "Transient ischaemic attack": 1, "Tremor": 1, "Ulcer": 1, "Underdose": 2, "Unevaluable event": 1, "Unresponsive to stimuli": 1, "Urinary tract infection": 1, "Urine analysis": 1, "Urticaria": 6, "Vaccination site erythema": 5, "Vaccination site induration": 1, "Vaccination site lymphadenopathy": 1, "Vaccination site mass": 1, "Vaccination site pain": 5, "Vaccination site pruritus": 4, "Vaccination site rash": 5, "Vaccination site swelling": 3, "Vaccination site warmth": 4, "Vaccine breakthrough infection": 5, "Vaccine positive rechallenge": 1, "Vision blurred": 1, "Vital functions abnormal": 3, "Vital signs measurement": 1, "Vomiting": 9, "Weight decreased": 1, "Weight increased": 1, "Wheezing": 1, "White blood cell count normal": 1}}