{"batchcode": "038B12A", "histograms": [{"histogram": {"Computerised tomogram normal": 1, "Magnetic resonance imaging head normal": 1, "Tinnitus": 1}, "batchcodes": ["024C21A", "038B12A"]}, {"histogram": {"COVID-19": 1, "SARS-CoV-2 test positive": 1}, "batchcodes": ["038B12A", "040A21A"]}, {"histogram": {"Nausea": 2, "Anxiety": 1, "Burning sensation": 1, "Chills": 1, "Dizziness": 1, "Dyspnoea": 1, "Hyperhidrosis": 1, "Muscle tightness": 1, "Paraesthesia oral": 1, "Pruritus": 1, "Tremor": 1}, "batchcodes": ["038B12A"]}], "Life Threatening Illnesses": 0, "Adverse Reaction Reports": 5, "Deaths": 0, "Company": "MODERNA", "Severe reports": null, "Lethality": null, "Disabilities": 0}