{"batchcode": "043AZIA", "histograms": [{"histogram": {"Fatigue": 4, "Muscle spasms": 4, "Headache": 3, "Pain": 3, "Pyrexia": 3, "Asthenia": 2, "Gait inability": 2, "Nausea": 2, "Urticaria": 2, "Vertigo": 2, "Axillary pain": 1, "Balance test": 1, "Blood creatinine increased": 1, "Burning sensation": 1, "COVID-19": 1, "Chest X-ray abnormal": 1, "Chills": 1, "Cough": 1, "Decreased appetite": 1, "Diarrhoea": 1, "Disorientation": 1, "Dizziness": 1, "Fibrin D dimer increased": 1, "Herpes zoster": 1, "Hyperhidrosis": 1, "Hypokalaemia": 1, "Lymphadenopathy": 1, "Menstrual disorder": 1, "Migraine": 1, "Muscular weakness": 1, "Myalgia": 1, "Neuralgia": 1, "Pain in extremity": 1, "Pruritus": 1, "Rash": 1, "SARS-CoV-2 test positive": 1, "Tenosynovitis": 1, "Vestibular function test": 1, "Vomiting": 1}, "batchcodes": ["043AZIA"]}], "Life Threatening Illnesses": 0, "Adverse Reaction Reports": 12, "Deaths": 0, "Company": "JANSSEN", "Severe reports": null, "Lethality": null, "Disabilities": 1}