{"batchcode": "043C21A", "histogram": {"Asthenia": 2, "Pyrexia": 2, "Aeromonas infection": 1, "COVID-19": 1, "COVID-19 pneumonia": 1, "Chest pain": 1, "Chest scan": 1, "Chills": 1, "Culture negative": 1, "Diarrhoea": 1, "Dizziness": 1, "Dyspnoea": 1, "Electrocardiogram": 1, "Extra dose administered": 1, "Hypoxia": 1, "Intensive care": 1, "Klebsiella infection": 1, "Nausea": 1, "Pain": 1, "Pleural effusion": 1, "Pneumonia": 1, "Sedation": 1, "Somnolence": 1, "Therapeutic response unexpected": 1, "Urinary tract infection": 1}, "Deaths": 0, "Adverse Reaction Reports": 5, "Company": "MODERNA", "Life Threatening Illnesses": 0, "Disabilities": 0}