{"batchcode": "046G21A", "histograms": [{"batchcodes": ["046G21A", "A1026"], "histogram": {"Acoustic stimulation tests": 1, "Foetal exposure during pregnancy": 1, "Heart rate variability test": 1, "Umbilical cord around neck": 1}}, {"batchcodes": ["046G21A"], "histogram": {"Dizziness": 4, "Chills": 3, "Pyrexia": 3, "Vomiting": 3, "Asthenia": 2, "Seizure": 2, "Abdominal pain": 1, "Chest pain": 1, "Headache": 1, "Hypersensitivity": 1, "Hypoaesthesia": 1, "Loss of consciousness": 1, "Malaise": 1, "Monoplegia": 1, "Nausea": 1, "Syncope": 1, "Vaccination site pain": 1}}]}