{"batchcode": "04F21A", "histograms": [{"histogram": {"COVID-19": 1, "SARS-CoV-2 test positive": 1, "Vaccine breakthrough infection": 1}, "batchcodes": ["011M20A", "037K20A", "04F21A"]}, {"histogram": {"Axillary pain": 1, "Breast mass": 1, "Breast pain": 1, "Extra dose administered": 1, "Fatigue": 1, "Mammogram": 1, "Ultrasound scan": 1}, "batchcodes": ["04F21A"]}], "Adverse Reaction Reports": 2, "Deaths": 0, "Disabilities": 0, "Life Threatening Illnesses": 0, "Company": "MODERNA", "Severe reports": null, "Lethality": null}