{"batchcode": "0661C21A", "histograms": [{"histogram": {"Blood test normal": 1, "COVID-19": 1, "Chest X-ray normal": 1, "Computerised tomogram thorax normal": 1, "Diarrhoea": 1, "Fatigue": 1, "Headache": 1, "Lacrimation increased": 1, "Pyrexia": 1, "SARS-CoV-2 test positive": 1, "Sinus congestion": 1}, "batchcodes": ["0661C21A"]}], "Adverse Reaction Reports": null, "Life Threatening Illnesses": null, "Lethality": null, "Deaths": null, "Company": null, "Severe reports": null, "Disabilities": null}