{"batchcode": "07F21A", "histogram": {"Acute respiratory failure": 1, "Anticoagulant therapy": 1, "COVID-19": 1, "COVID-19 pneumonia": 1, "Computerised tomogram thorax abnormal": 1, "Expired product administered": 1, "Heart rate irregular": 1, "Hypersensitivity": 1, "Hypokalaemia": 1, "Pulmonary embolism": 1, "Respiratory tract congestion": 1, "Therapeutic response unexpected": 1}, "Adverse Reaction Reports": 4, "Company": "MODERNA", "Disabilities": 0, "Life Threatening Illnesses": 0, "Deaths": 0}