{"batchcode": "1816024", "histograms": [{"histogram": {"Adverse event": 57, "Headache": 29, "Dizziness": 19, "Myalgia": 19, "Cellulitis": 17, "Nausea": 12, "Pyrexia": 12, "Chills": 8, "Anaphylactic reaction": 7, "Injection site pain": 7, "Injection site erythema": 6, "Injection site swelling": 6, "Paralysis": 6, "Encephalitis": 5, "Vomiting": 5, "Abdominal pain upper": 4, "Anaphylactoid reaction": 3, "Arthritis": 3, "Diarrhoea": 3, "Guillain-Barre syndrome": 3, "Adverse drug reaction": 2, "Hypersensitivity": 2, "Thrombocytopenic purpura": 2, "Blood parathyroid hormone": 1, "Blood test normal": 1, "Body temperature": 1, "COVID-19": 1, "Chest pain": 1, "Dyspnoea": 1, "Eye irritation": 1, "Generalised oedema": 1, "Goitre": 1, "Haematemesis": 1, "Hypoacusis": 1, "Lymphadenitis": 1, "Lymphadenopathy": 1, "Malaise": 1, "Overdose": 1, "Pericarditis": 1, "Rash": 1, "Rash pruritic": 1, "Seizure": 1, "Thyroid function test": 1, "Unevaluable event": 1, "Urticaria": 1}, "batchcodes": ["1816024"]}], "Adverse Reaction Reports": 118, "Deaths": 1, "Disabilities": 0, "Life Threatening Illnesses": 0, "Company": "JANSSEN", "Severe reports": 0.847457627118644, "Lethality": 0.847457627118644}