{"batchcode": "1C0081", "histograms": [{"histogram": {"Epstein-Barr virus infection": 1, "Fundoscopy": 1, "Hepatitis": 1, "Inappropriate schedule of product administration": 1, "Ophthalmic vein thrombosis": 1, "Optical coherence tomography": 1, "Pancreatitis": 1, "Perioral dermatitis": 1, "Pyrexia": 1}, "batchcodes": ["1C0081"]}], "Lethality": null, "Life Threatening Illnesses": 0, "Severe reports": null, "Deaths": 0, "Adverse Reaction Reports": 2, "Disabilities": 0, "Company": "PFIZER\\BIONTECH"}