{"batchcode": "1H058A_1101209", "histograms": [{"histogram": {"Adverse event": 1, "Angina unstable": 1, "Ascites": 1, "Cellulitis": 1, "Diabetic nephropathy": 1, "Discomfort": 1, "Echocardiogram": 1, "Electrocardiogram": 1, "Hepatic cirrhosis": 1, "Hepatic failure": 1, "Hyperlipidaemia": 1, "Liver disorder": 1, "Multiple organ dysfunction syndrome": 1, "Nephropathy": 1, "Renal failure": 1, "Septic shock": 1, "Splenomegaly": 1, "Thrombosis": 1, "Thyroid disorder": 1}, "batchcodes": ["1H058A_1101209"]}]}