{"Adverse Reaction Reports": 16, "Company": "PFIZER\\BIONTECH", "Deaths": 0, "Disabilities": 0, "Hospitalizations": 6, "Life-Threatening Illnesses": 1, "batchcode": "1I069A_1110106-", "histogram": {"Abdominal neoplasm": 1, "Abdominal pain": 1, "Abdominal pain upper": 1, "Allergic oedema": 1, "Altered state of consciousness": 2, "Angina pectoris": 1, "Arrhythmia": 2, "Arthralgia": 1, "Biopsy bone marrow": 1, "Blood creatine phosphokinase": 1, "Blood creatine phosphokinase MB": 1, "Blood glucose": 1, "Blood pressure measurement": 6, "Blood test": 3, "Body temperature": 2, "Bone scan": 1, "Chest discomfort": 3, "Chest pain": 5, "Cold sweat": 2, "Coma": 1, "Coma scale": 1, "Computerised tomogram abdomen": 1, "Computerised tomogram head": 1, "Congenital mitral valve incompetence": 1, "Cyanosis": 1, "Decreased activity": 1, "Decreased appetite": 1, "Dehydration": 1, "Dizziness": 2, "Dyspnoea": 2, "Echocardiogram": 1, "Electrocardiogram": 7, "Eye swelling": 1, "Facial paralysis": 1, "Fatigue": 1, "Haemorrhage intracranial": 1, "Headache": 2, "Heart rate": 4, "Hepatomegaly": 1, "Hypotension": 1, "Inappropriate schedule of product administration": 2, "Intravascular haemolysis": 1, "Investigation": 1, "Lymphadenitis": 1, "Lymphadenopathy": 1, "Magnetic resonance imaging": 1, "Metastases to bone": 1, "Metastases to liver": 1, "Mucosal dryness": 1, "Muscular weakness": 1, "Myocardial necrosis marker": 1, "Myocardial necrosis marker increased": 1, "Myocarditis": 1, "Nausea": 3, "Neuroblastoma": 1, "Overdose": 1, "Oxygen saturation": 2, "Pain": 1, "Pain in extremity": 1, "Palpitations": 2, "Platelet count": 1, "Pruritus": 3, "Pyrexia": 5, "Rash": 1, "Respiration abnormal": 1, "Respiratory distress": 1, "Respiratory rate": 1, "Sleep disorder": 1, "Syncope": 2, "Thrombocytopenia": 1, "Thrombosis": 1, "Troponin": 1, "Tumour marker test": 1, "Ultrasonic angiogram": 1, "Urine analysis": 2, "Urine output decreased": 1, "Urticaria": 1, "Vaccination site erythema": 1, "Vaccination site pain": 2, "Vaccination site swelling": 1, "Vision blurred": 1, "Vital signs measurement": 1, "Vomiting": 3}}