{"Adverse Reaction Reports": 5, "Company": "PFIZER\\BIONTECH", "Deaths": 0, "Disabilities": 0, "Hospitalizations": 1, "Life-Threatening Illnesses": 1, "batchcode": "2593", "histogram": {"Blood test": 1, "Cardiomyopathy": 1, "Computerised tomogram head": 1, "Computerised tomogram neck": 1, "Echocardiogram": 1, "Electrocardiogram": 2, "Electroencephalogram": 1, "Fatigue": 2, "Loss of consciousness": 1, "Magnetic resonance imaging head": 2, "Muscular weakness": 1, "Nausea": 1, "Neuralgia": 1, "Palpitations": 1, "Paralysis": 1, "Pyrexia": 1, "Seizure like phenomena": 1, "Syncope": 1, "Tinnitus": 2, "Ultrasound Doppler": 1}}