{"batchcode": "3246", "histogram": {"Headache": 5, "Chills": 2, "Injection site erythema": 2, "Injection site warmth": 2, "Magnetic resonance imaging": 2, "Pain": 2, "Pyrexia": 2, "SARS-CoV-2 test": 2, "Vomiting": 2, "Abdominal pain": 1, "Antibody test negative": 1, "Blood test abnormal": 1, "Breast feeding": 1, "Cerebral venous sinus thrombosis": 1, "Diarrhoea": 1, "Injection site pain": 1, "Injection site swelling": 1, "Myalgia": 1, "Nausea": 1, "Pain in extremity": 1, "Retching": 1, "SARS-CoV-2 antibody test": 1, "Scan": 1, "Seizure": 1, "Urticaria": 1, "Vasculitic rash": 1}, "Deaths": 0, "Adverse Reaction Reports": 13, "Disabilities": 1, "Company": "PFIZER\\BIONTECH", "Life Threatening Illnesses": 1}