{"Adverse Reaction Reports": 6, "Company": "NOVAVAX", "Deaths": 0, "Disabilities": 0, "Hospitalizations": 0, "Life-Threatening Illnesses": 0, "batchcode": "6024MF016", "histogram": {"Fall": 1, "Headache": 3, "Injection site erythema": 2, "Injection site induration": 2, "Injection site mass": 2, "Injection site reaction": 1, "Injection site swelling": 2, "Injection site warmth": 2, "Loss of consciousness": 1, "Lymphadenopathy": 3, "Mammogram": 2, "Mammogram abnormal": 1, "Mobility decreased": 1, "Pain in extremity": 1, "Syncope": 1, "Urticaria": 1, "Vaccination site erythema": 1, "Vaccination site induration": 1, "Vaccination site mass": 1, "Vaccination site swelling": 1, "Vaccination site warmth": 1}}