{"Adverse Reaction Reports": 16, "Company": "NOVAVAX", "Deaths": 0, "Disabilities": 0, "Hospitalizations": 4, "Life-Threatening Illnesses": 0, "batchcode": "6024MF013", "histogram": {"Abdominal pain upper": 1, "Ageusia": 1, "Blood potassium decreased": 1, "Blood pressure measurement": 1, "Blood sodium decreased": 1, "Brain fog": 1, "Breath sounds abnormal": 1, "Computerised tomogram": 3, "Contusion": 1, "Decreased appetite": 1, "Delusion": 3, "Diarrhoea": 1, "Dizziness": 3, "Dysgraphia": 3, "Erythema": 3, "Expired product administered": 1, "Extra dose administered": 1, "Feeding disorder": 1, "Fine motor skill dysfunction": 3, "Head injury": 1, "Hyperhidrosis": 2, "Immediate post-injection reaction": 2, "Influenza like illness": 1, "Injection site pain": 1, "Injection site rash": 2, "Laboratory test": 2, "Mental status changes": 3, "Muscle spasms": 2, "Muscle twitching": 2, "Musculoskeletal stiffness": 2, "Nausea": 2, "Pain": 2, "Pain in extremity": 1, "Posture abnormal": 1, "Pruritus": 1, "Rash erythematous": 2, "Sepsis": 3, "Skin warm": 2, "Swelling": 1, "Syncope": 2, "Unresponsive to stimuli": 3, "Vomiting": 1}}