{"batchcode": "AB0003", "histogram": {"SARS-CoV-2 test": 5, "Pyrexia": 4, "Headache": 3, "Pain": 3, "Back pain": 2, "COVID-19": 2, "Computerised tomogram": 2, "Drug ineffective": 2, "Dysgeusia": 2, "Dyspnoea": 2, "Fatigue": 2, "Feeling abnormal": 2, "Interchange of vaccine products": 2, "Lymphadenopathy": 2, "Malaise": 2, "Myalgia": 2, "Off label use": 2, "Abdominal pain upper": 1, "Anaphylactic reaction": 1, "Anosmia": 1, "Arrhythmia": 1, "Body temperature": 1, "Bone pain": 1, "Bradyphrenia": 1, "Breast enlargement": 1, "Cerebrovascular accident": 1, "Chills": 1, "Decreased appetite": 1, "Deep vein thrombosis": 1, "Dizziness": 1, "Eye pain": 1, "Facial paralysis": 1, "Heart rate": 1, "Heart rate increased": 1, "Hot flush": 1, "Hyposmia": 1, "Injection site pain": 1, "Lymph node pain": 1, "Migraine": 1, "Nausea": 1, "Pain in extremity": 1, "Peripheral coldness": 1, "Product use issue": 1, "Swelling": 1, "Tremor": 1}, "Hospitalizations": 2, "Deaths": 0, "Company": "UNKNOWN MANUFACTURER", "Life Threatening Illnesses": 4, "Adverse Reaction Reports": 37, "Disabilities": 5}