{"batchcode": "EL 0725", "histogram": {"Pyrexia": 7, "Body temperature": 6, "SARS-CoV-2 test": 6, "Blood pressure measurement": 5, "Fatigue": 5, "Vaccination failure": 5, "Asthenia": 4, "COVID-19": 4, "Vomiting": 4, "Asymptomatic COVID-19": 3, "Computerised tomogram head": 3, "Headache": 3, "Myalgia": 3, "Syncope": 3, "Vaccination site erythema": 3, "Vaccination site pain": 3, "Arrhythmia": 2, "Drug ineffective": 2, "Heart rate": 2, "Hot flush": 2, "Nasal congestion": 2, "Nasopharyngitis": 2, "Neurological examination": 2, "Oropharyngeal pain": 2, "Oxygen saturation": 2, "Pain in extremity": 2, "Vaccination site pruritus": 2, "Ageusia": 1, "Anaphylactic shock": 1, "Angina pectoris": 1, "Anosmia": 1, "Antibody test": 1, "Atrioventricular block complete": 1, "Blister": 1, "Blood pressure increased": 1, "Blood test": 1, "Bone pain": 1, "Burning sensation": 1, "Cardiac disorder": 1, "Chest pain": 1, "Chills": 1, "Computerised tomogram": 1, "Confusional state": 1, "Cough": 1, "Dermatitis herpetiformis": 1, "Diabetes mellitus management": 1, "Diarrhoea": 1, "Diarrhoea haemorrhagic": 1, "Dizziness": 1, "Dysphonia": 1, "Dyspnoea": 1, "Ear pain": 1, "Ear, nose and throat examination": 1, "Electrocardiogram": 1, "Electrocardiogram ambulatory": 1, "Electroencephalogram": 1, "Electromyogram": 1, "Enterocolitis haemorrhagic": 1, "Extrasystoles": 1, "Eye pain": 1, "Facial paralysis": 1, "Fraction of inspired oxygen": 1, "Guillain-Barre syndrome": 1, "Herpes zoster": 1, "High frequency ablation": 1, "Hyperpyrexia": 1, "Hypertension": 1, "Hypertensive crisis": 1, "Hyperthermia": 1, "Hypoacusis": 1, "Hypoaesthesia": 1, "Hypotension": 1, "Incorrect route of product administration": 1, "Investigation": 1, "Laboratory test": 1, "Laryngeal oedema": 1, "Laryngospasm": 1, "Loss of consciousness": 1, "Lymphoedema": 1, "Magnetic resonance imaging heart": 1, "Malaise": 1, "Muscular weakness": 1, "Myocardial infarction": 1, "Nausea": 1, "Orthostatic hypotension": 1, "Paraesthesia": 1, "Petechiae": 1, "Petit mal epilepsy": 1, "Platelet count": 1, "Post herpetic neuralgia": 1, "Postmenopausal haemorrhage": 1, "Pruritus": 1, "Pulmonary sensitisation": 1, "Sinusitis": 1, "Skin reaction": 1, "Somnolence": 1, "Tachycardia": 1, "Thirst": 1, "Urinary incontinence": 1, "Urticaria": 1, "Vaccination site dermatitis": 1, "Vaccination site oedema": 1, "Vaccination site swelling": 1, "Vertigo": 1, "White blood cell count": 1}, "Life Threatening Illnesses": 3, "Disabilities": 3, "Company": "PFIZER\\BIONTECH", "Adverse Reaction Reports": 36, "Deaths": 2}