{"batchcode": "EL 9269", "histogram": {"Chills": 10, "Fatigue": 10, "Pyrexia": 9, "Headache": 8, "Dyspnoea": 7, "Pain": 7, "Pain in extremity": 6, "Arthralgia": 5, "Dizziness": 5, "Lymphadenopathy": 4, "Nausea": 4, "Body temperature": 3, "Cough": 3, "Myalgia": 3, "Rash": 3, "SARS-CoV-2 test negative": 3, "Anosmia": 2, "Back pain": 2, "Body temperature increased": 2, "Chest pain": 2, "Computerised tomogram normal": 2, "Computerised tomogram thorax": 2, "Condition aggravated": 2, "Diarrhoea": 2, "Heart rate irregular": 2, "Herpes zoster": 2, "Hyperhidrosis": 2, "Lymph node pain": 2, "Muscle tightness": 2, "Rhinorrhoea": 2, "SARS-CoV-2 test positive": 2, "Sleep disorder": 2, "Urticaria": 2, "Vaccination site pain": 2, "Vertigo": 2, "Abnormal sensation in eye": 1, "Ageusia": 1, "Antinuclear antibody negative": 1, "Asthenia": 1, "Atrial fibrillation": 1, "Axillary pain": 1, "Biopsy": 1, "Blood creatinine increased": 1, "Blood pressure decreased": 1, "Blood pressure increased": 1, "Blood test": 1, "Blood urea increased": 1, "Bone pain": 1, "COVID-19": 1, "Cardiac monitoring abnormal": 1, "Chest X-ray": 1, "Chest X-ray normal": 1, "Chest discomfort": 1, "Computerised tomogram abdomen normal": 1, "Computerised tomogram pelvis": 1, "Computerised tomogram thorax normal": 1, "Decreased appetite": 1, "Delirium": 1, "Discomfort": 1, "Dysuria": 1, "Eye irritation": 1, "Eye pain": 1, "Feeling abnormal": 1, "Haemoglobin decreased": 1, "Head discomfort": 1, "Heart rate increased": 1, "Hypoaesthesia": 1, "Inflammation": 1, "Influenza like illness": 1, "Injected limb mobility decreased": 1, "Injection site erythema": 1, "Injection site nodule": 1, "Injection site pain": 1, "Insomnia": 1, "Interstitial lung disease": 1, "Joint range of motion decreased": 1, "Laboratory test normal": 1, "Magnetic resonance imaging": 1, "Magnetic resonance imaging normal": 1, "Malaise": 1, "Mean arterial pressure decreased": 1, "Menstrual disorder": 1, "Mydriasis": 1, "Nasal congestion": 1, "Night sweats": 1, "Oropharyngeal pain": 1, "Painful respiration": 1, "Pemphigoid": 1, "Peripheral coldness": 1, "Pharyngeal paraesthesia": 1, "Photophobia": 1, "Pruritus": 1, "Pulmonary embolism": 1, "Pulmonary function test normal": 1, "Purpura": 1, "Red blood cell abnormality": 1, "Reticulocyte count increased": 1, "Scan with contrast abnormal": 1, "Somnolence": 1, "Swelling": 1, "Swelling of eyelid": 1, "Tachycardia": 1, "Tinnitus": 1, "Transfusion": 1, "Tremor": 1, "Unevaluable event": 1, "Vaccination site erythema": 1, "Vaccination site swelling": 1, "Vision blurred": 1, "Vital functions abnormal": 1, "Vomiting": 1, "White blood cell count increased": 1, "X-ray normal": 1}, "Life Threatening Illnesses": 2, "Deaths": 0, "Company": "PFIZER\\BIONTECH", "Adverse Reaction Reports": 49, "Disabilities": 3}