{"batchcode": "EN602", "histograms": [{"histogram": {"Anxiety": 1, "Dry mouth": 1, "Eye pain": 1, "Micturition urgency": 1, "Vaginal haemorrhage": 1}, "batchcodes": ["E19264", "EN602"]}, {"histogram": {"Amnesia": 1, "Balance disorder": 1, "Brain operation": 1, "Death": 1, "Thrombosis": 1}, "batchcodes": ["EN602", "EN607"]}, {"histogram": {"COVID-19": 1}, "batchcodes": ["EN602", "ER2613"]}, {"histogram": {"Cough": 1, "Dyspnoea": 1, "Vaccine breakthrough infection": 1}, "batchcodes": ["EN602", "ER8736"]}, {"histogram": {"Chills": 3, "Fatigue": 2, "Pain": 2, "Pyrexia": 2, "Arthralgia": 1, "Back pain": 1, "Dehydration": 1, "Hyperhidrosis": 1, "Insomnia": 1, "Myalgia": 1, "Pain in extremity": 1, "Paranoia": 1}, "batchcodes": ["EN602"]}], "Life Threatening Illnesses": 0, "Adverse Reaction Reports": 7, "Deaths": 1, "Company": "PFIZER\\BIONTECH", "Severe reports": null, "Lethality": null, "Disabilities": 0}