{"batchcode": "ET8885-L664", "histograms": [{"histogram": {"SARS-CoV-2 test": 2, "Chills": 1, "Contusion": 1, "Diarrhoea": 1, "Fatigue": 1, "Glossitis": 1, "Glossodynia": 1, "Headache": 1, "Malaise": 1, "Myalgia": 1, "Nasopharyngitis": 1, "Nausea": 1, "Pyrexia": 1, "Tongue discolouration": 1, "Tongue disorder": 1, "Tongue erythema": 1, "Tongue ulceration": 1, "Vaccination site bruising": 1, "Vaccination site haemorrhage": 1, "Vaccination site pain": 1}, "batchcodes": ["ET8885-L664"]}], "Lethality": null, "Life Threatening Illnesses": 0, "Severe reports": null, "Deaths": 0, "Adverse Reaction Reports": 2, "Disabilities": 0, "Company": "PFIZER\\BIONTECH"}