{"batchcode": "EW6204", "histograms": [{"histogram": {"Ageusia": 1, "Anosmia": 1, "Headache": 1, "Respiratory tract congestion": 1, "Rhinorrhoea": 1}, "batchcodes": ["EL3302", "EW6204"]}, {"histogram": {"Acute respiratory failure": 1, "Anion gap normal": 1, "Arthralgia": 1, "Basophil count decreased": 1, "Basophil percentage decreased": 1, "Blood calcium normal": 1, "Blood chloride decreased": 1, "Blood creatinine normal": 1, "Blood glucose normal": 1, "Blood lactic acid normal": 1, "Blood magnesium increased": 1, "Blood potassium normal": 1, "Blood sodium decreased": 1, "Blood urea decreased": 1, "Breath sounds abnormal": 1, "COVID-19": 1, "COVID-19 pneumonia": 1, "Carbon dioxide normal": 1, "Chest X-ray abnormal": 1, "Chills": 1, "Cough": 1, "Dyspnoea": 1, "Dyspnoea exertional": 1, "Electrocardiogram": 1, "Eosinophil count decreased": 1, "Eosinophil percentage decreased": 1, "Fatigue": 1, "Glomerular filtration rate decreased": 1, "Haematocrit normal": 1, "Haemoglobin normal": 1, "Hypoxia": 1, "International normalised ratio increased": 1, "Lung infiltration": 1, "Lymphocyte count decreased": 1, "Lymphocyte percentage decreased": 1, "Mean cell haemoglobin concentration normal": 1, "Mean cell haemoglobin normal": 1, "Mean cell volume normal": 1, "Mean platelet volume normal": 1, "Monocyte count": 1, "Monocyte percentage": 1, "Myalgia": 1, "Nasal congestion": 1, "Neutrophil count": 1, "Neutrophil percentage increased": 1, "Pain": 1, "Platelet count decreased": 1, "Procalcitonin normal": 1, "Prothrombin time prolonged": 1, "Pyrexia": 1, "Red blood cell count normal": 1, "Red cell distribution width normal": 1, "Respiratory viral panel": 1, "SARS-CoV-2 test positive": 1, "Troponin T normal": 1, "Viral test negative": 1, "White blood cell count normal": 1}, "batchcodes": ["EN6202", "EW6204"]}, {"histogram": {"Vaccine positive rechallenge": 1}, "batchcodes": ["EW0180", "EW6204"]}, {"histogram": {"Fatigue": 4, "Headache": 2, "Nausea": 2, "Abdominal pain upper": 1, "Anaemia": 1, "Arthralgia": 1, "Autoimmune hepatitis": 1, "Biopsy bone marrow abnormal": 1, "Blood test normal": 1, "Chest X-ray": 1, "Chest discomfort": 1, "Chills": 1, "Computerised tomogram abdomen abnormal": 1, "Computerised tomogram normal": 1, "Dyspnoea": 1, "Echocardiogram abnormal": 1, "Electrocardiogram abnormal": 1, "Electrocardiogram normal": 1, "Hepatomegaly": 1, "Joint swelling": 1, "Laboratory test abnormal": 1, "Laboratory test normal": 1, "Loss of personal independence in daily activities": 1, "Malaise": 1, "Musculoskeletal stiffness": 1, "Myalgia": 1, "Pain": 1, "Pyrexia": 1, "Restless legs syndrome": 1, "Sinus bradycardia": 1, "Splenic infarction": 1, "Splenomegaly": 1, "Supraventricular tachycardia": 1, "Syncope": 1, "Ultrasound abdomen abnormal": 1, "Vaccination site pain": 1, "Vaccination site swelling": 1}, "batchcodes": ["EW6204"]}], "Life Threatening Illnesses": 2, "Adverse Reaction Reports": 9, "Deaths": 0, "Company": "PFIZER\\BIONTECH", "Severe reports": null, "Lethality": null, "Disabilities": 0}