{"Adverse Reaction Reports": 14, "Company": "PFIZER\\BIONTECH", "Deaths": 1, "Disabilities": 3, "Hospitalizations": 5, "Life-Threatening Illnesses": 1, "batchcode": "FF5111", "histogram": {"Abdominal distension": 1, "Angina pectoris": 1, "Aphasia": 1, "Arthralgia": 1, "Ascites": 1, "Asthenia": 4, "Back pain": 1, "Blood glucose decreased": 1, "Blood pressure measurement": 2, "Blood test": 1, "Body temperature": 1, "COVID-19": 1, "Cardiac failure congestive": 1, "Cardiac murmur": 1, "Cardiac murmur functional": 1, "Cataract": 1, "Chest discomfort": 1, "Chest pain": 4, "Chills": 1, "Cough": 2, "Death": 1, "Decreased appetite": 1, "Deep vein thrombosis": 1, "Dermatitis infected": 1, "Diabetes mellitus": 1, "Dizziness": 2, "Dyspnoea": 7, "Dysstasia": 1, "Erythema": 2, "Fatigue": 3, "Feeding disorder": 1, "Feeling cold": 1, "Food allergy": 1, "Gait inability": 1, "HIV infection": 1, "Haemoglobin": 1, "Headache": 3, "Heart rate": 3, "Heavy menstrual bleeding": 1, "Herpes zoster": 1, "Hypoaesthesia": 1, "Illness": 3, "Immunodeficiency": 1, "Impaired work ability": 1, "Inappropriate schedule of product administration": 4, "Influenza": 1, "Investigation": 1, "Jaundice": 1, "Laboratory test": 1, "Liver function test": 1, "Liver injury": 1, "Lymphadenitis": 1, "Malaise": 3, "Menstrual disorder": 1, "Myocardial infarction": 1, "Myocardial injury": 1, "Neck pain": 1, "Neoplasm malignant": 1, "Oedema": 1, "Oral mucosal blistering": 1, "Oxygen saturation": 2, "Pain": 2, "Pain in extremity": 2, "Peripheral swelling": 1, "Pneumonia": 1, "Post herpetic neuralgia": 1, "Pruritus": 1, "Pulmonary oedema": 1, "Rales": 1, "Rash": 2, "Rash pruritic": 1, "Renal disorder": 1, "Respiratory rate": 2, "Rhinorrhoea": 1, "SARS-CoV-2 test": 3, "Scan abnormal": 1, "Swelling": 2, "Throat tightness": 2, "Thrombosis": 1, "Transient ischaemic attack": 1, "Vaccination site swelling": 1, "Venous pressure jugular": 1, "Vomiting": 1}}