{"batchcode": "FL18027", "histograms": [{"histogram": {"Acute left ventricular failure": 1, "Arrhythmia": 1, "Atrial fibrillation": 1, "COVID-19": 1, "COVID-19 pneumonia": 1, "Cardiac failure congestive": 1, "Cardiomyopathy": 1, "Chest X-ray abnormal": 1, "Condition aggravated": 1, "Cough": 1, "Dyspnoea": 1, "Echocardiogram abnormal": 1, "Ejection fraction decreased": 1, "Electrocardiogram QRS complex normal": 1, "Electrocardiogram abnormal": 1, "Hypertension": 1, "Pulmonary oedema": 1, "SARS-CoV-2 test positive": 1, "Sleep disorder": 1, "Vaccine breakthrough infection": 1, "White blood cell count normal": 1}, "batchcodes": ["EP7534", "EW0153", "FL18027"]}]}