{"batchcode": "HD9869", "histogram": {"Arrhythmia": 1, "Atrial fibrillation": 1, "Conjunctival haemorrhage": 1, "Diplopia": 1, "Disease recurrence": 1, "Dizziness": 1, "Hallucination": 1, "Hypertension": 1, "Migraine with aura": 1, "Pain in extremity": 1, "Postmenopausal haemorrhage": 1, "Seizure": 1, "Sensory disturbance": 1, "Visual field defect": 1, "Visual impairment": 1}, "Company": "PFIZER\\BIONTECH", "Adverse Reaction Reports": 6, "Disabilities": 0, "Life Threatening Illnesses": 0, "Deaths": 0}