{"batchcode": "O42L2OA", "histograms": [{"histogram": {"Condition aggravated": 1, "Inflammation": 1, "Magnetic resonance imaging": 1, "Muscle spasms": 1, "Neurological examination": 1, "Pain in extremity": 1, "Rash papular": 1, "Rash pruritic": 1, "Skin abrasion": 1, "Skin lesion": 1, "Skin mass": 1, "Spinal pain": 1}, "batchcodes": ["O42L2OA"]}], "Lethality": null, "Life Threatening Illnesses": 0, "Severe reports": null, "Deaths": 0, "Adverse Reaction Reports": 2, "Disabilities": 0, "Company": "MODERNA"}