{"batchcode": "O46B21A", "histogram": {"Blister": 1, "Blood pressure measurement": 1, "Burning sensation": 1, "Chills": 1, "Discomfort": 1, "Dizziness": 1, "Dyspnoea": 1, "Erythema": 1, "Fatigue": 1, "Headache": 1, "Hot flush": 1, "Hypoaesthesia": 1, "Malaise": 1, "Nausea": 1, "Pain": 1, "Pain in extremity": 1, "Paraesthesia": 1, "Pruritus": 1, "Pyrexia": 1, "SARS-CoV-2 test negative": 1, "Skin discolouration": 1, "Swelling": 1, "Tenderness": 1, "Visual impairment": 1}, "Deaths": 0, "Adverse Reaction Reports": 3, "Company": "MODERNA", "Disabilities": 0, "Life Threatening Illnesses": 0}