{"batchcode": "SD0809", "histogram": {"Electrocardiogram": 2, "Balance disorder": 1, "Blood pressure increased": 1, "Blood test": 1, "Cerebrovascular accident": 1, "Chest discomfort": 1, "Computerised tomogram": 1, "Dyspnoea": 1, "Gait disturbance": 1, "Headache": 1, "Hypoaesthesia": 1, "Hypotension": 1, "Immunisation": 1, "Neck pain": 1, "Neurological examination": 1, "Paraesthesia": 1, "Vaccination site erythema": 1, "Vaccination site pain": 1, "Vaccination site swelling": 1}, "Company": "PFIZER\\BIONTECH", "Life Threatening Illnesses": 0, "Disabilities": 0, "Adverse Reaction Reports": 4, "Deaths": 0}