{"batchcode": "VNR1F03F082007", "histograms": [{"histogram": {"Abnormal faeces": 1, "Cardiovascular disorder": 1, "Dizziness": 1, "Dysgeusia": 1, "Fatigue": 1, "Haemorrhage": 1, "Headache": 1, "Hot flush": 1, "Insomnia": 1, "Malaise": 1, "Nausea": 1, "Pain in extremity": 1, "Premenstrual pain": 1, "Somnolence": 1, "Tendon pain": 1, "Tinnitus": 1, "Urine odour abnormal": 1}, "batchcodes": ["VNR1F03F082007"]}], "Deaths": 0, "Lethality": null, "Company": "PFIZER\\BIONTECH", "Adverse Reaction Reports": 1, "Disabilities": 0, "Life Threatening Illnesses": 0, "Severe reports": null}