{"batchcode": "EP6775", "histograms": [{"batchcodes": ["EP6775"], "histogram": {"Headache": 85, "Asthenia": 83, "Dizziness": 59, "Pain": 57, "Fatigue": 56, "Myalgia": 55, "Sensitive skin": 52, "Pyrexia": 45, "Arthralgia": 44, "Nausea": 44, "Body temperature": 41, "Dyspnoea": 41, "Respiratory distress": 38, "Tachycardia": 35, "Blood pressure measurement": 32, "Chills": 32, "Vaccination site pain": 32, "Induration": 24, "Nodule": 24, "Vomiting": 23, "Rhinorrhoea": 22, "Cough": 19, "Diarrhoea": 19, "Oropharyngeal pain": 19, "Body temperature increased": 18, "Rash": 18, "Abdominal pain": 17, "Irritability": 17, "Hypertension": 15, "Pruritus": 15, "Erythema": 14, "Haemorrhage": 13, "Lymphadenopathy": 13, "Decreased appetite": 12, "Hypovolaemic shock": 12, "Oedema": 12, "Blood pressure increased": 11, "Cellulitis": 10, "Heart rate": 10, "Oxygen saturation": 8, "Pain in extremity": 8, "Inflammation": 7, "Intussusception": 7, "Paraesthesia oral": 7, "Chest pain": 6, "Hypertensive crisis": 6, "Local reaction": 6, "Odynophagia": 6, "Oedema peripheral": 6, "Abscess": 5, "Back pain": 5, "Crying": 5, "Facial paralysis": 5, "Haematochezia": 5, "Hypotension": 5, "Palpitations": 5, "Paraesthesia": 5, "Bronchospasm": 4, "Feeling hot": 4, "Haemorrhagic disorder": 4, "Heart rate increased": 4, "Hyperhidrosis": 4, "Hypoaesthesia": 4, "Hypoaesthesia oral": 4, "Malaise": 4, "Muscular weakness": 4, "Pain assessment": 4, "Seizure": 4, "Anosmia": 3, "Disseminated Bacillus Calmette-Guerin infection": 3, "Dry mouth": 3, "Eye pain": 3, "Guillain-Barre syndrome": 3, "Hypokinesia": 3, "Oral discomfort": 3, "Respiratory rate": 3, "Syncope": 3, "Tremor": 3, "Vaccination site reaction": 3, "Vertigo": 3, "Anxiety": 2, "Axillary pain": 2, "Bell's palsy": 2, "Blood glucose": 2, "Blood pressure systolic increased": 2, "Dysgeusia": 2, "Eye irritation": 2, "Gait disturbance": 2, "Hyperthermia": 2, "Investigation": 2, "Movement disorder": 2, "Neck pain": 2, "Ocular hyperaemia": 2, "Oral disorder": 2, "Photopsia": 2, "Pneumonia": 2, "Respiratory arrest": 2, "Somnolence": 2, "Tinnitus": 2, "Vaccination error": 2, "Vaccination site cellulitis": 2, "Vaccination site erythema": 2, "Visual analogue scale": 2, "Vital signs measurement": 2, "Wrong technique in product usage process": 2, "Abdominal distension": 1, "Abdominal pain upper": 1, "Accidental overdose": 1, "Ageusia": 1, "Aggression": 1, "Anaphylactic reaction": 1, "Anaphylactic shock": 1, "Aphonia": 1, "Arrhythmia": 1, "Asthma": 1, "Autoimmune haemolytic anaemia": 1, "Blood lactate dehydrogenase": 1, "Blood pressure abnormal": 1, "Body mass index": 1, "Bradycardia": 1, "Cardio-respiratory arrest": 1, "Choking": 1, "Choluria": 1, "Colitis": 1, "Conjunctival haemorrhage": 1, "Coombs test": 1, "Dehydration": 1, "Diabetes mellitus management": 1, "Discomfort": 1, "Disturbance in attention": 1, "Drug hypersensitivity": 1, "Drug ineffective": 1, "Dysphagia": 1, "Dyspnoea exertional": 1, "Ear infection": 1, "Ecchymosis": 1, "Electrocardiogram": 1, "End stage renal disease": 1, "Eye discharge": 1, "Eye injury": 1, "Eyelid oedema": 1, "Eyelid ptosis": 1, "Face oedema": 1, "Facial spasm": 1, "Fall": 1, "Febrile convulsion": 1, "Feeling of despair": 1, "Gait inability": 1, "Gastrointestinal motility disorder": 1, "Gastrooesophageal reflux disease": 1, "Haemoglobin": 1, "Haemolytic anaemia": 1, "Hallucination": 1, "Heart rate abnormal": 1, "Hemiparesis": 1, "Hot flush": 1, "Hyperaemia": 1, "Hyperglycaemia": 1, "Hypersensitivity": 1, "Hypoglycaemia": 1, "Hypothermia": 1, "Hypoxia": 1, "Influenza like illness": 1, "Insomnia": 1, "Jaundice": 1, "Lacrimation increased": 1, "Limb discomfort": 1, "Loss of consciousness": 1, "Mobility decreased": 1, "Muscle strength normal": 1, "Myoclonic epilepsy": 1, "Nasal congestion": 1, "Nasopharyngitis": 1, "Nervous system disorder": 1, "Normochromic anaemia": 1, "Normocytic anaemia": 1, "Off label use": 1, "Optic neuritis": 1, "Oxygen saturation decreased": 1, "Paralysis": 1, "Pelvic pain": 1, "Peripheral swelling": 1, "Peripheral vascular disorder": 1, "Petechiae": 1, "Pharyngeal disorder": 1, "Pharyngeal ulceration": 1, "Photophobia": 1, "Physical examination": 1, "Presyncope": 1, "Product use issue": 1, "Respiratory disorder": 1, "Salivary hypersecretion": 1, "Sensation of foreign body": 1, "Sensitisation": 1, "Sensory loss": 1, "Sepsis": 1, "Septic shock": 1, "Skin lesion": 1, "Skin mass": 1, "Slow speech": 1, "Stevens-Johnson syndrome": 1, "Suspected COVID-19": 1, "Synovial cyst": 1, "Taste disorder": 1, "Thrombocytopenia": 1, "Thrombocytopenic purpura": 1, "Thrombosis": 1, "Ultrasound scan": 1, "Urinary tract infection": 1, "Vaccination complication": 1, "Vaccination site hypoaesthesia": 1, "Vaccination site induration": 1, "Vaccination site movement impairment": 1, "Vaccination site oedema": 1, "Vaccination site pruritus": 1, "Vision blurred": 1, "Visual acuity reduced": 1}}]}