{"batchcode": "025L02A", "histograms": [{"batchcodes": ["010M20A", "025L02A"], "histogram": {"Computerised tomogram abdomen abnormal": 1, "Haemangioma of liver": 1, "Hepatic enzyme increased": 1, "Menstruation irregular": 1}}, {"batchcodes": ["025L02A"], "histogram": {"Headache": 2, "Herpes zoster": 2, "Myalgia": 2, "Pyrexia": 2, "Arthralgia": 1, "Asthenia": 1, "Chills": 1, "Injection site reaction": 1, "Lymph node pain": 1, "Lymphadenopathy": 1, "Migraine": 1, "Nausea": 1, "Pain": 1, "Transient ischaemic attack": 1, "Tremor": 1, "Vomiting": 1}}]}