{"batchcode": "004C214", "histograms": [{"batchcodes": ["004C214", "010A21A", "012M20A"], "histogram": {"Amyloidosis": 1, "Anaemia": 1, "Biopsy bone": 1, "Biopsy skin": 1, "Blood test": 1, "Chronic lymphocytic leukaemia": 1, "Condition aggravated": 1, "General physical health deterioration": 1, "Influenza like illness": 1, "Infusion": 1, "Lymphoplasmacytoid lymphoma/immunocytoma": 1, "Transfusion": 1}}, {"batchcodes": ["004C214"], "histogram": {"Burning sensation": 1, "Chest discomfort": 1, "Fatigue": 1, "Feeding disorder": 1, "Headache": 1, "Heavy menstrual bleeding": 1, "Injection site erythema": 1, "Injection site pain": 1, "Injection site pruritus": 1, "Malaise": 1, "Menstrual disorder": 1, "Menstruation irregular": 1, "Muscle spasms": 1, "Nausea": 1, "Pain in extremity": 1, "Peripheral swelling": 1, "White blood cell count": 1, "X-ray": 1}}]}