{"batchcode": "5318", "histograms": [{"batchcodes": ["3248", "5318"], "histogram": {"Arthralgia": 1, "Body temperature increased": 1, "Fatigue": 1, "Hyperemesis gravidarum": 1, "Immediate post-injection reaction": 1, "Joint stiffness": 1, "Lymphadenopathy": 1, "Nausea": 1, "Somnolence": 1}}, {"batchcodes": ["5318", "EN6199"], "histogram": {"Arrhythmia": 1, "Electrocardiogram": 1, "Electrocardiogram ambulatory": 1, "Ventricular extrasystoles": 1}}, {"batchcodes": ["5318", "EN6205", "FF2593"], "histogram": {"COVID-19": 1, "Dizziness": 1, "Nausea": 1, "SARS-CoV-2 test positive": 1, "Tremor": 1, "Vomiting": 1}}, {"batchcodes": ["5318"], "histogram": {"Fatigue": 3, "Nausea": 2, "Asthenia": 1, "Cerebrovascular accident": 1, "Chest pain": 1, "Chills": 1, "Coagulation factor V level normal": 1, "Computerised tomogram thorax": 1, "Cough": 1, "Diarrhoea": 1, "Disorientation": 1, "Dizziness": 1, "Dysstasia": 1, "Electrocardiogram": 1, "Factor II mutation": 1, "Fall": 1, "Full blood count": 1, "Headache": 1, "Hyperhidrosis": 1, "Impaired work ability": 1, "Injection site bruising": 1, "Injection site pain": 1, "Laboratory test": 1, "Lip swelling": 1, "Magnetic resonance imaging": 1, "Muscular weakness": 1, "Pain": 1, "Productive cough": 1, "Pulmonary embolism": 1, "Pulmonary pain": 1, "Pyrexia": 1, "Swelling face": 1, "Swelling of eyelid": 1, "Ultrasound Doppler": 1, "Urine analysis": 1, "Urticaria": 1}}]}